README.md
setup.py
src/vdk/plugin/csv/csv_plugin.py
src/vdk/plugin/csv/csv_ingest_job/csv_ingest_step.py
src/vdk_csv.egg-info/PKG-INFO
src/vdk_csv.egg-info/SOURCES.txt
src/vdk_csv.egg-info/dependency_links.txt
src/vdk_csv.egg-info/entry_points.txt
src/vdk_csv.egg-info/requires.txt
src/vdk_csv.egg-info/top_level.txt